README.md
setup.py
enuma_elish/__init__.py
enuma_elish/asyncdns.py
enuma_elish/book.py
enuma_elish/common.py
enuma_elish/cryptor.py
enuma_elish/daemon.py
enuma_elish/eventloop.py
enuma_elish/local.py
enuma_elish/lru_cache.py
enuma_elish/manager.py
enuma_elish/server.py
enuma_elish/shell.py
enuma_elish/tcprelay.py
enuma_elish/tunnel.py
enuma_elish/udprelay.py
enuma_elish.egg-info/PKG-INFO
enuma_elish.egg-info/SOURCES.txt
enuma_elish.egg-info/dependency_links.txt
enuma_elish.egg-info/entry_points.txt
enuma_elish.egg-info/top_level.txt
enuma_elish/crypto/__init__.py
enuma_elish/crypto/aead.py
enuma_elish/crypto/hkdf.py
enuma_elish/crypto/mbedtls.py
enuma_elish/crypto/openssl.py
enuma_elish/crypto/rc4_md5.py
enuma_elish/crypto/sodium.py
enuma_elish/crypto/table.py
enuma_elish/crypto/util.py