Metadata-Version: 1.0
Name: enuma-elish
Version: 0.0.2
Summary: A fast tunnel proxy  extension from ss ,which help you get through firewalls
Home-page: https://github.com/f0cklinux/enuma-elish
Author: f0cklinux
Author-email: no-one-controll@gmail.com
License: http://www.apache.org/licenses/LICENSE-2.0
Platform: UNKNOWN
